corva_data_datasetdepth/__init__.py
corva_data_datasetdepth/api_client.py
corva_data_datasetdepth/api_response.py
corva_data_datasetdepth/configuration.py
corva_data_datasetdepth/exceptions.py
corva_data_datasetdepth/py.typed
corva_data_datasetdepth/rest.py
corva_data_datasetdepth/api/__init__.py
corva_data_datasetdepth/api/corva_dataset_depth_api.py
corva_data_datasetdepth/models/__init__.py
corva_data_datasetdepth/models/corva_dataset_depth.py
corva_data_datasetdepth/models/http_validation_error.py
corva_data_datasetdepth-1.0.1.dist-info/METADATA
corva_data_datasetdepth-1.0.1.dist-info/WHEEL
corva_data_datasetdepth-1.0.1.dist-info/top_level.txt
corva_data_datasetdepth-1.0.1.dist-info/RECORD
